docassemble.docusign-0.2.1-py3.8-nspkg.pth
docassemble/docusign/__init__.py
docassemble/docusign/da_docusign.py
docassemble/docusign/data/questions/docusign_auth.yml
docassemble/docusign/data/questions/docusign_test_interview.yml
docassemble/docusign/data/sources/README.md
docassemble/docusign/data/static/README.md
docassemble/docusign/data/templates/README.md
docassemble.docusign-0.2.1.dist-info/LICENSE
docassemble.docusign-0.2.1.dist-info/METADATA
docassemble.docusign-0.2.1.dist-info/WHEEL
docassemble.docusign-0.2.1.dist-info/namespace_packages.txt
docassemble.docusign-0.2.1.dist-info/top_level.txt
docassemble.docusign-0.2.1.dist-info/RECORD
