Metadata-Version: 2.1
Name: docassemble.docusign
Version: 0.2.1
Summary: Python docassemble package for integrating with DocuSign
Home-page: https://github.com/radiant-law/docassemble-docusign
Author: Radiant Law, Theo Hamilton
Author-email: alex.hamilton@radiantlaw.com
License: The MIT License (MIT)
Project-URL: Radiant Law, https://radiantlaw.com
Project-URL: Source, https://github.com/radiant-law/docassemble-docusign
Keywords: docassemble docusign development
Platform: UNKNOWN
Classifier: Development Status :: 3 - Alpha
Classifier: Intended Audience :: Developers
Classifier: Topic :: Software Development :: Build Tools
Classifier: License :: OSI Approved :: MIT License
Classifier: Programming Language :: Python :: 3.5
Requires-Dist: PyJWT
Requires-Dist: requests
